{"id": "69b7cacb67e4ab7aa9773b1e5010cc0fd98cc08f", "recommendations": ["TRGSPUQ128E0780DA5", "TRGWBFK128F92EE885", "TRDZLYT128F4265A6F", "TRTQDER128F92DE72A", "TRMJXVS12903CACEDC", "TRSUNLB128E078180C", "TRLDJDG128F425F36C", "TROIYSD128F423EFFB", "TRRJQES128EF35675B", "TRJSQQT128F149F9B4", "TRUVNIJ128F92FD67D", "TRXJEJP128F14595A8", "TRSSAAP128F14979B6", "TRFBHLO128F92DE722", "TRGQVNH128F92F62A2", "TREFXKL128F148D0B0", "TRQVCXZ128F4298756", "TRSMTSC128E0788E08", "TRMLFIC128F4228CFD", "TRPWMGN128E078F2B8", "TRGNBVA12903CA735B", "TRJFFJI128F92E71E9", "TRJMYWD128E078ED31", "TRHQKZL128E0781A2C", "TRLQXVU128F934CF2D", "TRASGIZ128F9337F92", "TRROTDF128F931C028", "TRBUGXE128F428CD28", "TROBTGE128F429E591", "TRBHQZM128F42A52D2", "TRKKSRH128F426473F", "TRDCQIN128F42B84F8", "TRDEZCI12903C9A6AD", "TRAJPIQ128F14819A8", "TRYQSJG128E078EC88", "TRYDWIS128F935A452", "TRRDAMS128E0785DD3", "TRNMLOQ128EF340A40", "TRFWHUG128F14995B3", "TRZOMHO128F429BBFE", "TRVWQEV128F932799A", "TROIQMT128E0792994", "TRDGGGO12903CFE37C", "TRASQGR128F14557AA", "TRKTRKM128F4280BB6", "TRNIEVN128F148D021", "TRMEQQJ128F9336536", "TRBIVUY128F148724E", "TRIABXW128F42727D6", "TRNLXJM128F4289801"], "metrics": {"P": 25, "TP": 0, "precision": 0, "recall": 0, "f1": 0, "average precision": 0, "reciprocal rank": 0}}