{"id": "b44a7b18e5861d6b5c0094e43239191cbe5ff4e1", "recommendations": ["TRKHARN128F146DA7A", "TRULNMQ128F92E1FDA", "TRVCFUI128F92E1D42", "TRKDBVR128F935A643", "TRWIVLD12903CA9D35", "TRDFNWO128F92DFBA5", "TRVKTHJ128F424D875", "TRYZAMO128E079125F", "TRYCNEZ128F427B8D4", "TRKWXAG128EF340672", "TRDVUST128F4280D13", "TRKMWHB128E078ED8A", "TRJHALL128F92C48B6", "TRGUJRG128E079290A", "TRAJPUF128E0784808", "TROMXUF128EF35EE85", "TRKEIZP12903D05324", "TROOXQV128F932B6EF", "TRVGNYX128F93173C3", "TRGLEPF128F93379E9", "TRILXCN128F92F41C6", "TRZUBVA128F1469484", "TRYHWLD128F426BF7D", "TRDWQHL128F147BD31", "TRJIIBZ128F148D69A", "TRXPSPE128EF33FB50", "TRWGYLJ128F92CC96A", "TRNTALF128EF343800", "TRVYXUG128F933AD8F", "TRHQPDN12903CEA4B1", "TRGNIHW128E0789D37", "TRDWBCU128F426C536", "TRFDGFW128F4286BFF", "TRVWFPD128F423BCE2", "TROIXIC128F427B6F6", "TRKNVRW128F9309A57", "TRNIIFM128E078E1CD", "TRUTULC128F4293712", "TRNDWLI128EF340671", "TRLIYFS128F148855B", "TRXGWZE128F429DB94", "TRDQAWQ128F93379DF", "TRZKJFH128E0793EAC", "TRJVDZZ128E078FA46", "TRWAJII128F4294A1E", "TRNRJUN128F42AE2BC", "TRQXTTC128F4264434", "TRZVEHE128F92F3A75", "TRWSLFM128F429DBA2", "TRCAJOM128F1488559"], "metrics": {"P": 29, "TP": 0, "precision": 0, "recall": 0, "f1": 0, "average precision": 0, "reciprocal rank": 0}}